rrnafinder/__init__.py
rrnafinder/cli.py
rrnafinder/pipeline.py
rrnafinder/versions.py
rrnafinder/rRNA_data/plants/rRNA.bed
rrnafinder/rRNA_data/plants/rRNA.fa
rrnafinder/rRNA_data/plants/rRNA.gene.fa
rrnafinder/rRNA_data/plants/rRNA_18_20S.fa
rRNAFinder-0.0.3.dist-info/LICENSE
rRNAFinder-0.0.3.dist-info/METADATA
rRNAFinder-0.0.3.dist-info/WHEEL
rRNAFinder-0.0.3.dist-info/entry_points.txt
rRNAFinder-0.0.3.dist-info/top_level.txt
rRNAFinder-0.0.3.dist-info/RECORD
