Metadata-Version: 2.1
Name: rRNAFinder
Version: 0.0.3
Summary: A python tool for identify rRNA gene in plant genome.
Home-page: https://github.com/SouthernCD/rRNAFinder
Author: Yuxing Xu
Author-email: xuyuxing@mail.kib.ac.cn
License: UNKNOWN
Platform: UNKNOWN
Requires-Python: >=3.5
License-File: LICENSE
Requires-Dist: toolbiox (>=0.0.40)
Requires-Dist: hugep2g (>=1.0.1)
Requires-Dist: bcbio-gff (>=0.6.6)
Requires-Dist: biopython (<=1.80)
